devbrain-1.1.9.dist-info/licenses/LICENSE
mcp_server/__init__.py
mcp_server/server.py
devbrain-1.1.9.dist-info/METADATA
devbrain-1.1.9.dist-info/WHEEL
devbrain-1.1.9.dist-info/entry_points.txt
devbrain-1.1.9.dist-info/top_level.txt
devbrain-1.1.9.dist-info/RECORD
