Metadata-Version: 2.4
Name: devbrain
Version: 1.1.9
Summary: A FastMCP server for DevBrain stdio communication.
Author-email: Anton <anton@mimecam.com>
License-Expression: MIT
Project-URL: Homepage, https://github.com/mimeCam/mcp-devbrain-stdio
Project-URL: Bug Tracker, https://github.com/mimeCam/mcp-devbrain-stdio/discussions
Classifier: Programming Language :: Python :: 3.10
Classifier: Operating System :: OS Independent
Classifier: Intended Audience :: Developers
Requires-Python: >=3.10
License-File: LICENSE
Requires-Dist: fastmcp
Requires-Dist: requests
Dynamic: license-file
